{
   "micrownet" : [
      "female_person"
   ],
   "google" : [
      "/url?q=http://www.thefreedictionary.com/female%2Bperson&sa=U&ei=ZX3YUYSNK8bAtQbO1oCQAg&ved=0CBoQFjAA&usg=AFQjCNHGy5n-_jO1q6HnWvGxgySvGE1YHw",
      "/url?q=https://www.vocabulary.com/dictionary/female%2520person&sa=U&ei=ZX3YUYSNK8bAtQbO1oCQAg&ved=0CB4QFjAB&usg=AFQjCNGY6am2pY4hqtB7e-j4kV40lise4g",
      "/url?q=http://dictionary.reference.com/browse/female%2Bperson&sa=U&ei=ZX3YUYSNK8bAtQbO1oCQAg&ved=0CCAQFjAC&usg=AFQjCNEdwKIVIXUWWqXkQXIQZGTn062mtg",
      "/url?q=http://www.audioenglish.org/dictionary/female_person.htm&sa=U&ei=ZX3YUYSNK8bAtQbO1oCQAg&ved=0CCMQFjAD&usg=AFQjCNHbSITNnxvUO9YD7zTiShgfs5Nr7g",
      "/url?q=http://forum.wordreference.com/showthread.php%3Ft%3D2033019&sa=U&ei=ZX3YUYSNK8bAtQbO1oCQAg&ved=0CCYQFjAE&usg=AFQjCNFxWNOAE_iRih-samP8Ui4l9Mhd8Q"
   ],
   "micro" : [
      "female_offspring",
      "individual",
      "object",
      "mortal",
      "somebody",
      "being",
      "foster-sister",
      "person",
      "living_thing",
      "girl_wonder",
      "someone",
      "organism",
      "causal_agent",
      "female_child",
      "physical_object",
      "animate_thing",
      "whole",
      "unit",
      "physical_entity",
      "woman",
      "soul",
      "little_girl",
      "girl",
      "causal_agency",
      "adult_female",
      "female_person",
      "foster_sister",
      "entity",
      "cause",
      "female"
   ],
   "micro-www" : {
      "female_person" : [
         ""
      ]
   },
   "Lists" : [],
   "micro-www-search" : [],
   "micro-relation" : []
}
